lzhprt/__init__.py
lzhprt/_base.py
lzhprt/_tool.py
lzhprt/container.py
lzhprt/pchunk.py
lzhprt/pdiy.py
lzhprt/unit.py
lzhprt-1.0.0.dist-info/METADATA
lzhprt-1.0.0.dist-info/WHEEL
lzhprt-1.0.0.dist-info/top_level.txt
lzhprt-1.0.0.dist-info/RECORD
